.coveragerc
.gitignore
.travis.yml
LICENSE
MANIFEST.in
README.md
logger.conf.example
setup.cfg
setup.py
tox.ini
contrail_api_cli/__init__.py
contrail_api_cli/auth.py
contrail_api_cli/client.py
contrail_api_cli/command.py
contrail_api_cli/completer.py
contrail_api_cli/context.py
contrail_api_cli/exceptions.py
contrail_api_cli/idl_parser.py
contrail_api_cli/main.py
contrail_api_cli/manager.py
contrail_api_cli/parser.py
contrail_api_cli/resource.py
contrail_api_cli/schema.py
contrail_api_cli/style.py
contrail_api_cli/utils.py
contrail_api_cli.egg-info/PKG-INFO
contrail_api_cli.egg-info/SOURCES.txt
contrail_api_cli.egg-info/dependency_links.txt
contrail_api_cli.egg-info/entry_points.txt
contrail_api_cli.egg-info/requires.txt
contrail_api_cli.egg-info/top_level.txt
contrail_api_cli/commands/__init__.py
contrail_api_cli/commands/cat.py
contrail_api_cli/commands/du.py
contrail_api_cli/commands/edit.py
contrail_api_cli/commands/exec.py
contrail_api_cli/commands/kv.py
contrail_api_cli/commands/ln.py
contrail_api_cli/commands/ls.py
contrail_api_cli/commands/man.py
contrail_api_cli/commands/python.py
contrail_api_cli/commands/relative.py
contrail_api_cli/commands/rm.py
contrail_api_cli/commands/schema.py
contrail_api_cli/commands/shell.py
contrail_api_cli/commands/tree.py
contrail_api_cli/schemas/1.10/all_cfg.xsd
contrail_api_cli/schemas/1.10/bfd_schema.xsd
contrail_api_cli/schemas/1.10/bgp_schema.xsd
contrail_api_cli/schemas/1.10/ietf-bfd-schema.xsd
contrail_api_cli/schemas/1.10/ietf-l3vpn-schema.xsd
contrail_api_cli/schemas/1.10/loadbalancer.xsd
contrail_api_cli/schemas/1.10/routing_policy.xsd
contrail_api_cli/schemas/1.10/services.xsd
contrail_api_cli/schemas/1.10/smi-base.xsd
contrail_api_cli/schemas/1.10/vnc_cfg.xsd
contrail_api_cli/schemas/1.10/xmpp_enet.xsd
contrail_api_cli/schemas/1.10/xmpp_multicast.xsd
contrail_api_cli/schemas/1.10/xmpp_unicast.xsd
contrail_api_cli/schemas/2.21/all_cfg.xsd
contrail_api_cli/schemas/2.21/bfd_schema.xsd
contrail_api_cli/schemas/2.21/bgp_schema.xsd
contrail_api_cli/schemas/2.21/ietf-bfd-schema.xsd
contrail_api_cli/schemas/2.21/ietf-l3vpn-schema.xsd
contrail_api_cli/schemas/2.21/loadbalancer.xsd
contrail_api_cli/schemas/2.21/routing_policy.xsd
