Metadata-Version: 1.1
Name: contrail-api-cli
Version: 0.2.1
Summary: Simple CLI program to browse Contrail API server
Home-page: http://www.github.com/eonpatapon/contrail-api-cli
Author: Jean-Philippe Braun
Author-email: eon@patapon.info
License: MIT
Keywords: contrail api cli
Platform: UNKNOWN
Classifier: Development Status :: 5 - Production/Stable
Classifier: Intended Audience :: Developers
Classifier: Topic :: Software Development :: User Interfaces
Classifier: License :: OSI Approved :: MIT License
Classifier: Programming Language :: Python :: 2.7
Classifier: Programming Language :: Python :: 3.4
